odoo/addons/pos_customer_comment/README.rst
odoo/addons/pos_customer_comment/__init__.py
odoo/addons/pos_customer_comment/__manifest__.py
odoo/addons/pos_customer_comment/demo/res_partner.xml
odoo/addons/pos_customer_comment/i18n/es.po
odoo/addons/pos_customer_comment/i18n/fr.po
odoo/addons/pos_customer_comment/i18n/it.po
odoo/addons/pos_customer_comment/i18n/pos_customer_comment.pot
odoo/addons/pos_customer_comment/models/__init__.py
odoo/addons/pos_customer_comment/models/pos_session.py
odoo/addons/pos_customer_comment/models/res_partner.py
odoo/addons/pos_customer_comment/readme/CONTRIBUTORS.rst
odoo/addons/pos_customer_comment/readme/CREDITS.rst
odoo/addons/pos_customer_comment/readme/DESCRIPTION.rst
odoo/addons/pos_customer_comment/readme/ROADMAP.rst
odoo/addons/pos_customer_comment/readme/USAGE.rst
odoo/addons/pos_customer_comment/static/description/icon.png
odoo/addons/pos_customer_comment/static/description/index.html
odoo/addons/pos_customer_comment/static/description/pos_customer_form.png
odoo/addons/pos_customer_comment/static/description/pos_customer_tree.png
odoo/addons/pos_customer_comment/static/description/res_partner_form.png
odoo/addons/pos_customer_comment/static/src/css/pos_customer_comment.scss
odoo/addons/pos_customer_comment/static/src/js/PartnerDetailsEdit.esm.js
odoo/addons/pos_customer_comment/static/src/xml/PartnerDetailsEdit.xml
odoo/addons/pos_customer_comment/static/src/xml/PartnerLine.xml
odoo/addons/pos_customer_comment/tests/__init__.py
odoo/addons/pos_customer_comment/tests/test_module.py
odoo/addons/pos_customer_comment/tests/tours/PosCustomerComment.tour.js
odoo/addons/pos_customer_comment/views/view_res_partner.xml
odoo_addon_pos_customer_comment-16.0.1.0.3.dist-info/METADATA
odoo_addon_pos_customer_comment-16.0.1.0.3.dist-info/WHEEL
odoo_addon_pos_customer_comment-16.0.1.0.3.dist-info/top_level.txt
odoo_addon_pos_customer_comment-16.0.1.0.3.dist-info/RECORD
