Metadata-Version: 2.1
Name: odoo-addon-pos_customer_comment
Version: 16.0.1.0.3
Summary: Display Customer comment in the PoS front office and allow to edit and save it by the cashier
Home-page: https://github.com/OCA/pos
Author: GRAP,Odoo Community Association (OCA)
Author-email: support@odoo-community.org
License: AGPL-3
Classifier: Programming Language :: Python
Classifier: Framework :: Odoo
Classifier: Framework :: Odoo :: 16.0
Classifier: License :: OSI Approved :: GNU Affero General Public License v3
Requires-Python: >=3.10
Requires-Dist: odoo<16.1dev,>=16.0a
